aure
